zanwango/__init__.py
zanwango/apps.py
zanwango/conf/__init__.py
zanwango/conf/models.py
django_zanwango-0.1.0.dist-info/LICENSE
django_zanwango-0.1.0.dist-info/METADATA
django_zanwango-0.1.0.dist-info/WHEEL
django_zanwango-0.1.0.dist-info/RECORD
